rcd_pyutils/__init__.py
rcd_pyutils/database_manager/__init__.py
rcd_pyutils/database_manager/elasticsearch_operator.py
rcd_pyutils/database_manager/gcloud_operator.py
rcd_pyutils/database_manager/mysql_operator.py
rcd_pyutils/database_manager/redshift_operator.py
rcd_pyutils/database_manager/s3_operator.py
rcd_pyutils/database_manager/snowflake_operator.py
rcd_pyutils/dataclass_manager/__init__.py
rcd_pyutils/dataclass_manager/raw_data_file.py
rcd_pyutils/decorator_manager/__init__.py
rcd_pyutils/decorator_manager/debug_decorator.py
rcd_pyutils/decorator_manager/functional_decorator.py
rcd_pyutils/file_manager/__init__.py
rcd_pyutils/file_manager/file_detector.py
rcd_pyutils/file_manager/file_operator.py
rcd_pyutils/file_manager/file_writer.py
rcd_pyutils/pandas_manager/__init__.py
rcd_pyutils/pandas_manager/checker.py
rcd_pyutils/pandas_manager/detector.py
rcd_pyutils/pandas_manager/io.py
rcd_pyutils/pandas_manager/manipulator.py
rcd_pyutils/pandas_manager/normalizer.py
rcd_pyutils-0.1.32.dist-info/LICENSE
rcd_pyutils-0.1.32.dist-info/METADATA
rcd_pyutils-0.1.32.dist-info/WHEEL
rcd_pyutils-0.1.32.dist-info/top_level.txt
rcd_pyutils-0.1.32.dist-info/RECORD
